dbwrapper/__init__.py
dbwrapper/_query.py
dbwrapper/_util.py
dbwrapper/connection_pool.py
dbwrapper/migration.py
dbwrapper/postgresql/__init__.py
dbwrapper/postgresql/_conn.py
dbwrapper/postgresql/_db.py
dbwrapper/postgresql/_query.py
dbwrapper/postgresql/_table.py
dbwrapper/sqlite/__init__.py
dbwrapper/sqlite/_conn.py
dbwrapper/sqlite/_db.py
dbwrapper/sqlite/_funcs.py
dbwrapper/sqlite/_query.py
dbwrapper/sqlite/_table.py
dbwrapper/sqlite/_util.py
dbwrapper/sqlite/dtypes.py
dbwrapper_python-0.1.1.dist-info/LICENSE
dbwrapper_python-0.1.1.dist-info/METADATA
dbwrapper_python-0.1.1.dist-info/WHEEL
dbwrapper_python-0.1.1.dist-info/top_level.txt
dbwrapper_python-0.1.1.dist-info/RECORD
