Metadata-Version: 2.1
Name: dbwrapper-python
Version: 0.1.1
Summary: Wraps SQL Syntax into a python API.
Home-page: https://github.com/azalac/dbwrapper
Author: azalac
License: UNKNOWN
Platform: UNKNOWN
Provides-Extra: postgres
Requires-Dist: psycopg2 ; extra == 'postgres'
